Lab08 D1/ROM4kx8/ROM4kx8.v
//Jonathan Pu c. 19249
//Memoria ROM 4kx8
module rom_mem(
    input wire [11:0]address, //direccion
    output wire [7:0]data
    ); 

    reg[7:0] my_mem [0:4095]; //8 bits de ancho, 4096 depth memory
    
    initial begin
        $readmemh("memory.list.txt", my_mem); //leer el archivo
    end
    assign data = my_mem[address]; //asignar a la salida la direccion
endmodule

Lab08 D1/ROM4kx8/ROM4kx8_tb.v
//testbench ROM

module testbench();
    reg [11:0]address;
    wire [7:0]data;

    rom_mem memtb(address, data);
        
        initial begin
        $display("\n");
        $display("Testbench memory rom");
        $display("--------------------");
        $display("    Address         |      Data    ");
        $monitor("    %b    |    %b    ", address, data); //leer los datos del archivo
        address = 12'b000000000000; //0
        #1 address = 12'b000000000001; //1
        #1 address = 12'b000000010000; //10
        #1 address = 12'b000000010001; //11
        #1 address = 12'b000000010010; //12
        #1 address = 12'b000000010011; //13
        #1 address = 12'b000000010100; //14
        #1 address = 12'b000100000000; //100
        #1 address = 12'b000100000001; //101
        #1 address = 12'b000100000010; //102
        #1 address = 12'b000100000011; //103
        #1 address = 12'b000100000100; //104
    
        end

        initial
        #25 $finish;

        //GTK wave
        initial begin
            $dumpfile("ROM4kx8_tb.vcd"); //nombre del documento
            $dumpvars(0, testbench); //modulo de testbench
        end

endmodule

Lab08 D1/ROM4kx8/ROM4kx8_tb.vcd
$date
	Sat Oct 24 17:16:05 2020
$end
$version
	Icarus Verilog
$end
$timescale
	1ps
$end
$scope module testbench $end
$var wire 8 ! data [7:0] $end
$var reg 12 " address [11:0] $end
$scope module memtb $end
$var wire 12 # address [11:0] $end
$var wire 8 $ data [7:0] $end
$upscope $end
$upscope $end
$enddefinitions $end
#0
$dumpvars
b10101010 $
b0 #
b0 "
b10101010 !
$end
#1
b10111011 !
b10111011 $
b1 "
b1 #
#2
b11001 !
b11001 $
b10000 "
b10000 #
#3
b1010 !
b1010 $
b10001 "
b10001 #
#4
b10010 !
b10010 $
b10010 "
b10010 #
#5
b1 !
b1 $
b10011 "
b10011 #
#6
b10000 !
b10000 $
b10100 "
b10100 #
#7
b11111111 !
b11111111 $
b100000000 "
b100000000 #
#8
b10111100 !
b10111100 $
b100000001 "
b100000001 #
#9
b11001011 !
b11001011 $
b100000010 "
b100000010 #
#10
b11001010 !
b11001010 $
b100000011 "
b100000011 #
#11
b11001101 !
b11001101 $
b100000100 "
b100000100 #
