Lab04 D1/Ejercicio01_02/Lab04Ejercicio01_02.v
// Ejercicio04 Lab04 Jonathan Pu c. 19249

/* Ejercicio01 Tabla 1 Con gate modelling
Ecuacion a implementar Y = B'C'+ AC + A'C' */

module Tabla1a(input wire inA, inB, inC, output wire Y); 

    wire NA, NB, NC, A1, A2, A3;
    not (NA, inA);
    not (NB, inB);
    not (NC, inC);
    and (A1, NB, NC);
    and (A2, inA, inC);
    and (A3, NA, NC);
    or (Y, A1, A2, A3);

endmodule

/*Ejercicio01 Tabla 2 con Operadores logicos
Funcion a implementar Y = B'*/

module Tabla1b(input wire inA, inB, inC, output wire Y);
    
    assign Y = (~inB);

endmodule 

/*Ejercicio01 Tabla 3 con gate modelling
Funcion a implementar Y = A'B'C'D' + A'B'C*D + A'*B*C'*D 
 + A'*B*C*D' + A*B*C'*D' + A*B*C*D + A*B'*C'*D + A*B'*C*D'*/

module Tabla1c(input wire inA, inB, inC, inD, output wire Y);
    wire NA, NB, NC, ND, A1, A2, A3, A4, A5, A6, A7, A8;
    not (NA, inA);
    not (NB, inB);
    not (NC, inC);
    not (ND, inD);
    and (A1, NA, NB, NC, ND);
    and (A2, NA, NB, inC, inD);
    and (A3, NA, inB, NC, inD);
    and (A4, NA, inB, inC, ND);
    and (A5, inA, inB, NC, ND);
    and (A6, inA, inB, inC, inD);
    and (A7, inA, NB, NC, inD);
    and (A8, inA, NB, inC, ND);
    or (Y, A1, A2, A3, A4, A5, A6, A7, A8);

endmodule

/*Ejercicio01 Tabla 4 con operadores logicos
Ecuacion a implementar Y = A*B + A*C + B'*D'*/

module Tabla1d(input wire inA, inB, inC, inD, output wire Y);
    assign Y = (inA & inB) | (inA & inC) | (~inB & ~inD);

endmodule

/* Ejercicio02 Tabla 1 con gate modelling 
Ecuacion a implementar Y = B'*C'*D' + A*C' + A*B' + A*D' */

module Tabla2a(input wire inA, inB, inC, inD, output wire Y);

    wire NB, NC, ND, A1, A2, A3, A4;

    not (NB, inB);
    not (NC, inC);
    not (ND, inD);
    and (A1, NB, NC, ND);
    and (A2, inA, NC);
    and (A3, inA, NB);
    and (A4, inA, ND);
    or (Y, A1, A2, A3, A4);

endmodule

/* Ejercicio02 Tabla 2 con operadores 
Ecuacion a implementar Y = B' + C */

module Tabla2b(input wire inA, inB, inC, output wire Y);

    assign Y = (~inB) | (inC);

endmodule

/* Ejercicio02 Tabla 3 con gate modelling
Ecuacion a implementar Y = C'*D + B + A*D */

module Tabla2c(input wire inA, inB, inC, inD, output wire Y);

    wire NC, A1, A2;

    not (NC, inC);
    and (A1, NC, inD);
    and (A2, inA, inD);
    or (Y, A1, A2, inB);

endmodule

/* Ejercicio02 Tabla 4 con operadores
Ecuacion a implementar Y = A'*C' + B */

module Tabla2d(input wire inA, inB, inC, output wire Y);

    assign Y = (~inA & ~inC) | (inB);

endmodule

Lab04 D1/Ejercicio01_02/Lab04Ejercicio01_02_tb.v
// Jonathan Pu c. 19249

module testbench();
    reg p1, p2, p3, p4, p5, p6, p7, p8, p9, p10, p11, p12, p13, p14;
    //Juntando las tablas que tienen tres variables de entradas
    wire out1, out2, out3, out4;
    //Para las tablas que tienen cuatro variables de entrada
    wire out5, out6, out7, out8;

    //Las primeras dos tablas del ejercicio1
     Tabla1a T1a(p1, p2, p3, out1);
     Tabla1b T1b(p1, p2, p3, out2);

    initial begin
        #1
        $display("\n");
        $display(" Tabla 1.1 y 1.2  ");
        $display("A  B  C  |  Y1  Y2");
        $display("---------|--------");
        $monitor("%b  %b  %b  |  %b  %b", p1, p2, p3, out1, out2);
            //Entradas comienzan todas en 0
            p1 = 0; p2 = 0; p3 = 0;
        #1 p3 = 1;
        #1 p2 = 1; p3 = 0;
        #1 p3 = 1;
        #1 p1 = 1; p2 = 0; p3 = 0;
        #1 p3 = 1;
        #1 p2 = 1; p3 = 0;
        #1 p3 = 1;
    end

    //Tabla 3 y 4 del ejercicio01
    Tabla1c T1c(p4, p5, p6, p7, out3);
    Tabla1d T1d(p4, p5, p6, p7, out4);
             
    initial begin
    #9
    $display("\n");
    $display(" Tabla 1.3 y 1.4  ");
    $display("A  B  C  D  |  Y1  Y2");
    $display("------------|--------");
    $monitor("%b  %b  %b  %b  |  %b  %b", p4, p5, p6, p7, out3, out4);
        //Todas las entradas comienzan en 0
        p4 = 0; p5 = 0; p6 = 0; p7 = 0;
    #1 p7 = 1;
    #1 p6 = 1; p7 = 0;
    #1 p7 = 1;
    #1 p5 = 1; p6 = 0; p7 = 0;
    #1 p7 = 1;
    #1 p6 = 1; p7 = 0;
    #1 p7 = 1;
    #1 p4 = 1; p5 = 0; p6 = 0; p7 = 0;
    #1 p7 = 1;
    #1 p6 = 1; p7 = 0;
    #1 p7 = 1;
    #1 p5 = 1; p6 = 0; p7 = 0;
    #1 p7 = 1;
    #1 p6 = 1; p7 = 0;
    #1 p7 = 1;

    end 

    //Tabla 2.2 y 2.4 (ejercicio02)
    Tabla2b T2b(p8, p9, p10, out5);
    Tabla2d T2d(p8, p9, p10, out6);

    initial begin
    #25
    $display("\n");
    $display(" Tabla 2.b y 2.d ");
    $display("A  B  C  |  Y1  Y2");
    $display("---------|--------");
    $monitor("%b  %b  %b  |  %b  %b", p8, p9, p10, out5, out6);
    //Entradas comienzan todas en 1
        p8 = 1; p9 = 1; p10 = 1;
    #1 p10 = 0;
    #1 p9 = 0; p10 = 1;
    #1 p10 = 0;
    #1 p8 = 0; p9 = 1; p10 = 1;
    #1 p10 = 0;
    #1 p9 = 0; p10 = 1;
    #1 p10 = 0;
        
    end

    //Tabla 2.1 y 2.3 (ejercicio02)
    Tabla2a T2a(p11, p12, p13, p14, out7);
    Tabla2c T2c(p11, p12, p13, p14, out8);

    initial begin
    #33
    $display("\n");
    $display(" Tabla 2.a y 2.c  ");
    $display("A  B  C  D  |  Y1  Y2");
    $display("------------|--------");
    $monitor("%b  %b  %b  %b  |  %b  %b", p11, p12, p13, p14, out7, out8);
        //Entradas comienzan todas en 1
        p11 = 1; p12 = 1; p13 = 1; p14 = 1;
    #1 p14 = 0;
    #1 p13 = 0; p14 = 1;
    #1 p14 = 0;
    #1 p12 = 0; p13 = 1; p14 = 1;
    #1 p14 = 0;
    #1 p13 = 0; p14 = 1;
    #1 p14 = 0;
    #1 p11 = 0; p12 = 1; p13 = 1; p14 = 1;
    #1 p14 = 0;
    #1 p13 = 0; p14 = 1;
    #1 p14 = 0;
    #1 p12 = 0; p13 = 1; p14 = 1;
    #1 p14 = 0;
    #1 p13 = 0; p14 = 1;
    #1 p14 = 0;

    end

    //Fin de codigo
    initial
        #50 $finish;

    //GTK Wave
    initial begin
        $dumpfile("Lab04Ejercicio01_02_tb.vcd");
        $dumpvars(0, testbench);

    end


endmodule //Fin de modulo de testbench para todas las tablas

Lab04 D1/Ejercicio01_02/Lab04Ejercicio01_02_tb.vcd
$date
	Sun Aug 09 05:40:16 2020
$end
$version
	Icarus Verilog
$end
$timescale
	1ps
$end
$scope module testbench $end
$var wire 1 ! out8 $end
$var wire 1 " out7 $end
$var wire 1 # out6 $end
$var wire 1 $ out5 $end
$var wire 1 % out4 $end
$var wire 1 & out3 $end
$var wire 1 ' out2 $end
$var wire 1 ( out1 $end
$var reg 1 ) p1 $end
$var reg 1 * p10 $end
$var reg 1 + p11 $end
$var reg 1 , p12 $end
$var reg 1 - p13 $end
$var reg 1 . p14 $end
$var reg 1 / p2 $end
$var reg 1 0 p3 $end
$var reg 1 1 p4 $end
$var reg 1 2 p5 $end
$var reg 1 3 p6 $end
$var reg 1 4 p7 $end
$var reg 1 5 p8 $end
$var reg 1 6 p9 $end
$scope module T1a $end
$var wire 1 7 A1 $end
$var wire 1 8 A2 $end
$var wire 1 9 A3 $end
$var wire 1 : NA $end
$var wire 1 ; NB $end
$var wire 1 < NC $end
$var wire 1 ( Y $end
$var wire 1 ) inA $end
$var wire 1 / inB $end
$var wire 1 0 inC $end
$upscope $end
$scope module T1b $end
$var wire 1 ' Y $end
$var wire 1 ) inA $end
$var wire 1 / inB $end
$var wire 1 0 inC $end
$upscope $end
$scope module T1c $end
$var wire 1 = A1 $end
$var wire 1 > A2 $end
$var wire 1 ? A3 $end
$var wire 1 @ A4 $end
$var wire 1 A A5 $end
$var wire 1 B A6 $end
$var wire 1 C A7 $end
$var wire 1 D A8 $end
$var wire 1 E NA $end
$var wire 1 F NB $end
$var wire 1 G NC $end
$var wire 1 H ND $end
$var wire 1 & Y $end
$var wire 1 1 inA $end
$var wire 1 2 inB $end
$var wire 1 3 inC $end
$var wire 1 4 inD $end
$upscope $end
$scope module T1d $end
$var wire 1 % Y $end
$var wire 1 1 inA $end
$var wire 1 2 inB $end
$var wire 1 3 inC $end
$var wire 1 4 inD $end
$upscope $end
$scope module T2a $end
$var wire 1 I A1 $end
$var wire 1 J A2 $end
$var wire 1 K A3 $end
$var wire 1 L A4 $end
$var wire 1 M NB $end
$var wire 1 N NC $end
$var wire 1 O ND $end
$var wire 1 " Y $end
$var wire 1 + inA $end
$var wire 1 , inB $end
$var wire 1 - inC $end
$var wire 1 . inD $end
$upscope $end
$scope module T2b $end
$var wire 1 $ Y $end
$var wire 1 5 inA $end
$var wire 1 6 inB $end
$var wire 1 * inC $end
$upscope $end
$scope module T2c $end
$var wire 1 P A1 $end
$var wire 1 Q A2 $end
$var wire 1 R NC $end
$var wire 1 ! Y $end
$var wire 1 + inA $end
$var wire 1 , inB $end
$var wire 1 - inC $end
$var wire 1 . inD $end
$upscope $end
$scope module T2d $end
$var wire 1 # Y $end
$var wire 1 5 inA $end
$var wire 1 6 inB $end
$var wire 1 * inC $end
$upscope $end
$upscope $end
$enddefinitions $end
#0
$dumpvars
xR
xQ
xP
xO
xN
xM
xL
xK
xJ
xI
xH
xG
xF
xE
xD
xC
xB
xA
x@
x?
x>
x=
x<
x;
x:
x9
x8
x7
x6
x5
x4
x3
x2
x1
x0
x/
x.
x-
x,
x+
x*
x)
x(
x'
x&
x%
x$
x#
x"
x!
$end
#1
1(
17
19
1<
1;
1'
1:
08
00
0/
0)
#2
0(
07
09
0<
10
#3
1(
19
1<
0;
0'
00
1/
#4
0(
09
0<
10
#5
1(
17
1<
1;
1'
0:
00
0/
1)
#6
07
0<
18
10
#7
0(
1<
08
0;
0'
00
1/
#8
1(
0<
18
10
#9
1&
1%
1=
1H
1G
0>
1F
0?
0@
1E
0A
0B
0C
0D
04
03
02
01
#10
0&
0%
0=
0H
14
#11
1%
1H
0G
04
13
#12
1&
0%
0H
1>
14
#13
0&
1H
1G
0>
0F
04
03
12
#14
1&
0H
1?
14
#15
1&
1@
1H
0?
0G
04
13
#16
0&
0@
0H
14
#17
1%
1H
1G
1F
0E
04
03
02
11
#18
1&
0%
0H
1C
14
#19
1&
1%
1D
1H
0C
0G
04
13
#20
0&
0D
0H
14
#21
1&
1A
1H
1G
0F
04
03
12
#22
0&
0A
0H
14
#23
1H
0G
04
13
#24
1&
0H
1B
14
#25
1$
1#
1*
16
15
#26
0$
0*
#27
1$
0#
1*
06
#28
0*
#29
1#
1*
16
05
#30
0$
0*
#31
0#
1$
1*
06
#32
1#
0*
#33
0"
0L
0J
0I
0K
0O
0P
0N
0R
0M
1!
1Q
1.
1-
1,
1+
#34
1"
1L
1O
0Q
0.
#35
0L
1J
0O
1P
1Q
1N
1R
1.
0-
#36
1L
1O
0P
0Q
0.
#37
0L
0J
1K
0O
1Q
0N
0R
1M
1!
1.
1-
0,
#38
1L
0!
1O
0Q
0.
#39
0L
1!
1J
0O
1P
1Q
1N
1R
1.
0-
#40
1I
1L
0!
1O
0P
0Q
0.
#41
0"
0I
0O
0N
0R
0M
1!
0J
0K
0L
1.
1-
1,
0+
#42
1O
0.
#43
0O
1P
1N
1R
1.
0-
#44
1O
0P
0.
#45
0O
0N
0R
1M
0!
1.
1-
0,
#46
1O
0.
#47
1!
0O
1P
1N
1R
1.
0-
#48
1"
1I
0!
1O
0P
0.
