Lab10 D1/Ejercicio01_10/CircuitoA.v
//Jonathan Pu c. 19249
//FF tipo D
//un bit
module FFD(input wire clk, reset, En, D, output reg Q);

    always@(posedge clk or posedge reset) begin
        if(reset)
            Q <= 1'b0;
        else if (En)
            Q <= D;
    end
endmodule

//dos bits
module FFD2(input wire clk, reset, En,
            input wire [1:0]D2,
            output wire [1:0]Q2);

    FFD a(clk, reset, En, D2[1], Q2[1]);
    FFD b(clk, reset, En, D2[0], Q2[0]);
endmodule

//cuatro bits
module FFD4(input wire clk, reset, En,
            input wire [3:0]D4,
            output wire [3:0]Q4);
    
    FFD2 a(clk, reset, En, D4[3:2], Q4[3:2]);
    FFD2 b(clk, reset, En, D4[1:0], Q4[1:0]);
endmodule

//8 bits con entrada de 8 y dos salidas de 4
module FFD8(input wire clk, reset, En,
            input wire [7:0]D8,
            output wire [3:0]Q8a,
            output wire [3:0]Q8b);
    FFD4 a(clk, reset, En, D8[7:4], Q8a);
    FFD4 b(clk, reset, En, D8[3:0], Q8b);
endmodule

//Jonathan Pu c. 19249
//Contador de 12 bits con enable y load

module cont12(
    input wire clk,
    input wire reset,
    input wire enable,
    input wire loact, //bit que activa la carga
    input wire [11:0]load, //carga de 12bits
    output reg [11:0]cont //salida de 12bits
    );

        always @(posedge clk or posedge reset or loact or load) begin //si LA y load cambia tambien se ejecuta el always
            if (reset)
                cont <= 12'b000000000000; //comienza en cero el contador
            else if (loact)
                cont <= load; //si el enable esta desactivado, el load pasa a la salida
            else if (enable)
                cont <= cont + 1; //a lo que tenia la salida se le suma 1
        end

endmodule

//Jonathan Pu c. 19249
//Memoria ROM 4kx8
module rom_mem(
    input wire [11:0]address, //direccion
    output wire [7:0]data
    ); 

    reg[7:0] my_mem [0:4095]; //8 bits de ancho, 4096 depth memory
    
    initial begin
        $readmemh("memory.list.txt", my_mem); //leer el archivo
    end
    assign data = my_mem[address]; //asignar a la salida la direccion
endmodule

module CircuitoA(input wire clk,
                reset,
                en_PC,
                en_Fetch,
                loact,
                input wire [11:0]load,
                output wire [3:0]instr,
                output wire [3:0]oprnd,
                output wire [7:0]program_byte /*sale de program ROM
                                              y entra a Fetch*/);
                                                      
    wire [11:0]cont;

cont12 a(clk, reset, en_PC, loact, load, cont);
rom_mem b(cont, program_byte);
FFD8 c(clk, reset, en_Fetch, program_byte, instr, oprnd);

endmodule

Lab10 D1/Ejercicio01_10/CircuitoA_tb.v
//tb circuito A

module tb();

    reg clk;
    reg reset;
    reg en_PC;
    reg en_Fetch;
    reg loact;
    reg [11:0]load;
    wire [3:0]instr;
    wire [3:0]oprnd;
    wire [7:0]program_byte;

    always
    #1 clk = ~clk;

    CircuitoA a(clk, reset, en_PC, en_Fetch, loact, load, instr, oprnd, program_byte);

    initial begin
        #1
        $display("\n");
        $display("-------------------------Testbench Circuito A--------------------------------------------");
        $display(" clk | rst | en_PC | en_Fetch | loact |    load        ||  instr | oprnd  |  program_byte ");
        $display("-----------------------------------------------------------------------------------------");
        $monitor(" %b   | %b   |   %b   |    %b     |  %b    | %b   || %b   | %b   |  %b ", clk, reset, en_PC, en_Fetch, loact, load, instr, oprnd, program_byte);
        clk = 0; reset = 1; en_PC = 0; en_Fetch = 0; loact = 0; load = 12'b000000000000;
        #2 reset = 0; en_PC = 1; en_Fetch = 1; loact = 0; //deberia desplegar el valor que hay en address 1
        #2 reset = 0; en_PC = 1; en_Fetch = 1; loact = 0; //no hay nada en esa localidad
        #2 reset = 0; en_PC = 1; en_Fetch = 1; loact = 1; load = 12'b000000010000; //deberia desplegar la pos. 12
        #2 reset = 0; en_PC = 1; en_Fetch = 1; loact = 0;
        #2 reset = 0; en_PC = 1; en_Fetch = 1; loact = 1; load = 12'b000100000000;
    end

    initial 
    #15 $finish;

    //GTK WAVE
    initial begin
        $dumpfile("CircuitoA_tb.vcd");
        $dumpvars(0, tb);
    end

endmodule

Lab10 D1/Ejercicio01_10/CircuitoA_tb.vcd
$date
	Fri Nov 06 22:49:51 2020
$end
$version
	Icarus Verilog
$end
$timescale
	1ps
$end
$scope module tb $end
$var wire 8 ! program_byte [7:0] $end
$var wire 4 " oprnd [3:0] $end
$var wire 4 # instr [3:0] $end
$var reg 1 $ clk $end
$var reg 1 % en_Fetch $end
$var reg 1 & en_PC $end
$var reg 1 ' loact $end
$var reg 12 ( load [11:0] $end
$var reg 1 ) reset $end
$scope module a $end
$var wire 1 $ clk $end
$var wire 1 % en_Fetch $end
$var wire 1 & en_PC $end
$var wire 1 ' loact $end
$var wire 12 * load [11:0] $end
$var wire 1 ) reset $end
$var wire 8 + program_byte [7:0] $end
$var wire 4 , oprnd [3:0] $end
$var wire 4 - instr [3:0] $end
$var wire 12 . cont [11:0] $end
$scope module a $end
$var wire 1 $ clk $end
$var wire 1 & enable $end
$var wire 1 ' loact $end
$var wire 12 / load [11:0] $end
$var wire 1 ) reset $end
$var reg 12 0 cont [11:0] $end
$upscope $end
$scope module b $end
$var wire 12 1 address [11:0] $end
$var wire 8 2 data [7:0] $end
$upscope $end
$scope module c $end
$var wire 8 3 D8 [7:0] $end
$var wire 1 % En $end
$var wire 1 $ clk $end
$var wire 1 ) reset $end
$var wire 4 4 Q8b [3:0] $end
$var wire 4 5 Q8a [3:0] $end
$scope module a $end
$var wire 4 6 D4 [3:0] $end
$var wire 1 % En $end
$var wire 1 $ clk $end
$var wire 1 ) reset $end
$var wire 4 7 Q4 [3:0] $end
$scope module a $end
$var wire 2 8 D2 [1:0] $end
$var wire 1 % En $end
$var wire 1 $ clk $end
$var wire 1 ) reset $end
$var wire 2 9 Q2 [1:0] $end
$scope module a $end
$var wire 1 : D $end
$var wire 1 % En $end
$var wire 1 $ clk $end
$var wire 1 ) reset $end
$var reg 1 ; Q $end
$upscope $end
$scope module b $end
$var wire 1 < D $end
$var wire 1 % En $end
$var wire 1 $ clk $end
$var wire 1 ) reset $end
$var reg 1 = Q $end
$upscope $end
$upscope $end
$scope module b $end
$var wire 2 > D2 [1:0] $end
$var wire 1 % En $end
$var wire 1 $ clk $end
$var wire 1 ) reset $end
$var wire 2 ? Q2 [1:0] $end
$scope module a $end
$var wire 1 @ D $end
$var wire 1 % En $end
$var wire 1 $ clk $end
$var wire 1 ) reset $end
$var reg 1 A Q $end
$upscope $end
$scope module b $end
$var wire 1 B D $end
$var wire 1 % En $end
$var wire 1 $ clk $end
$var wire 1 ) reset $end
$var reg 1 C Q $end
$upscope $end
$upscope $end
$upscope $end
$scope module b $end
$var wire 4 D D4 [3:0] $end
$var wire 1 % En $end
$var wire 1 $ clk $end
$var wire 1 ) reset $end
$var wire 4 E Q4 [3:0] $end
$scope module a $end
$var wire 2 F D2 [1:0] $end
$var wire 1 % En $end
$var wire 1 $ clk $end
$var wire 1 ) reset $end
$var wire 2 G Q2 [1:0] $end
$scope module a $end
$var wire 1 H D $end
$var wire 1 % En $end
$var wire 1 $ clk $end
$var wire 1 ) reset $end
$var reg 1 I Q $end
$upscope $end
$scope module b $end
$var wire 1 J D $end
$var wire 1 % En $end
$var wire 1 $ clk $end
$var wire 1 ) reset $end
$var reg 1 K Q $end
$upscope $end
$upscope $end
$scope module b $end
$var wire 2 L D2 [1:0] $end
$var wire 1 % En $end
$var wire 1 $ clk $end
$var wire 1 ) reset $end
$var wire 2 M Q2 [1:0] $end
$scope module a $end
$var wire 1 N D $end
$var wire 1 % En $end
$var wire 1 $ clk $end
$var wire 1 ) reset $end
$var reg 1 O Q $end
$upscope $end
$scope module b $end
$var wire 1 P D $end
$var wire 1 % En $end
$var wire 1 $ clk $end
$var wire 1 ) reset $end
$var reg 1 Q Q $end
$upscope $end
$upscope $end
$upscope $end
$upscope $end
$upscope $end
$upscope $end
$enddefinitions $end
#0
$dumpvars
xQ
xP
xO
xN
bx M
bx L
xK
xJ
xI
xH
bx G
bx F
bx E
bx D
xC
xB
xA
x@
bx ?
bx >
x=
x<
x;
x:
bx 9
bx 8
bx 7
bx 6
bx 5
bx 4
bx 3
bx 2
bx 1
bx 0
bx /
bx .
bx -
bx ,
bx +
bx *
x)
bx (
x'
x&
x%
x$
bx #
bx "
bx !
$end
#1
1:
0<
1@
0B
1H
0J
1N
0P
b10 8
b10 >
b10 F
b10 L
b1010 6
b1010 D
b10101010 !
b10101010 +
b10101010 2
b10101010 3
b0 .
b0 0
b0 1
0;
b0 9
0=
0A
b0 #
b0 -
b0 5
b0 7
b0 ?
0C
0I
b0 G
0K
0O
b0 "
b0 ,
b0 4
b0 E
b0 M
0Q
b0 (
b0 *
b0 /
0'
0%
0&
1)
0$
#2
1$
#3
0$
1%
1&
0)
#4
1B
1P
b11 >
b11 L
b1011 6
b1011 D
b10111011 !
b10111011 +
b10111011 2
b10111011 3
b1 .
b1 0
b1 1
b10 9
1;
b1010 #
b1010 -
b1010 5
b1010 7
b10 ?
1A
b10 G
1I
b1010 "
b1010 ,
b1010 4
b1010 E
b10 M
1O
1$
#5
0$
#6
x:
x<
x@
xB
xH
xJ
xN
xP
bx 8
bx >
bx F
bx L
bx 6
bx D
bx !
bx +
bx 2
bx 3
b10 .
b10 0
b10 1
b1011 "
b1011 ,
b1011 4
b1011 E
b11 M
1Q
b1011 #
b1011 -
b1011 5
b1011 7
b11 ?
1C
1$
#7
0:
0<
0@
1B
1H
0J
0N
1P
b0 8
b1 >
b10 F
b1 L
b1 6
b1001 D
b11001 !
b11001 +
b11001 2
b11001 3
b10000 .
b10000 0
b10000 1
0$
b10000 (
b10000 *
b10000 /
1'
#8
b0 9
0;
b1 #
b1 -
b1 5
b1 7
b1 ?
0A
b1001 "
b1001 ,
b1001 4
b1001 E
b1 M
0O
1$
#9
0B
1N
0P
b0 >
b10 L
b0 6
b1010 D
b1010 !
b1010 +
b1010 2
b1010 3
b10001 .
b10001 0
b10001 1
0$
0'
#10
1B
0H
b1 >
b0 F
b1 6
b10 D
b10010 !
b10010 +
b10010 2
b10010 3
b10010 .
b10010 0
b10010 1
0Q
b1010 "
b1010 ,
b1010 4
b1010 E
b10 M
1O
b0 #
b0 -
b0 5
b0 7
b0 ?
0C
1$
#11
1:
1<
1@
1H
1J
1P
b11 8
b11 >
b11 F
b11 L
b1111 6
b1111 D
b11111111 !
b11111111 +
b11111111 2
b11111111 3
b100000000 .
b100000000 0
b100000000 1
0$
b100000000 (
b100000000 *
b100000000 /
1'
#12
1;
b11 9
1=
1A
b1111 #
b1111 -
b1111 5
b1111 7
b11 ?
1C
b11 G
1K
b1111 "
b1111 ,
b1111 4
b1111 E
b11 M
1Q
1$
