Lab08 D1/ALU/ALU.v
//Jonathan Pu c.19249
//implementacion de ALU

module ALU(
    input wire [3:0]A, //entrada A
    input wire [3:0]B, //entrada b
    input wire [2:0]S, //selector
    output reg [3:0]Y //salida de ALU
                    );

    always@(A, B, S) //verificar cambios en A, B o S
        begin
            case(S)
                3'b000: Y = A & B; //A AND B
                3'b001: Y = A | B; //A OR B
                3'b010: Y = A + B; //A + B
                3'b011: Y = 4'b0000; //not used
                3'b100: Y = A & ~B;//A AND B'
                3'b101: Y = A | ~B;//A OR B'
                3'b110: Y = A - B;//A - B
                3'b111: Y = (A < B) ? 1:0;//SLT
                default: Y = 4'b0000; //todo seteado en 0
            endcase
        end
endmodule

Lab08 D1/ALU/ALU_tb.v
//testbench ALU

module testbench();
    reg [3:0]A;
    reg [3:0]B;
    reg [2:0]S;
    wire [3:0]Y;

    ALU tb(A, B, S, Y);

        initial begin
        #1
        $display("\n");
        $display("Testbench ALU");
        $display("--------------------");
        $display("|  A |   B  |  S  || Y");
        $monitor(" %b | %b | %b || %b", A, B, S, Y);
        A = 4'b0010; B = 4'b0011; S = 3'b000;
        #1 A = 4'b1100; B = 4'b1011; S = 3'b001;
        #1 A = 4'b1010; B = 4'b0101; S = 3'b010;
        #1 A = 4'b1111; B = 4'b1111; S = 3'b011;
        #1 A = 4'b0001; B = 4'b0000; S = 3'b100;
        #1 A = 4'b0110; B = 4'b1001; S = 3'b101;
        #1 A = 4'b1110; B = 4'b0001; S = 3'b110;
        #1 A = 4'b1101; B = 4'b1011; S = 3'b111;
        end

    initial
    #15 $finish;

    //GTK wave
    initial begin
        $dumpfile("ALU_tb.vcd"); //nombre del documento
        $dumpvars(0, testbench); //modulo de testbench
    end

endmodule

Lab08 D1/ALU/ALU_tb.vcd
$date
	Sat Oct 24 16:37:56 2020
$end
$version
	Icarus Verilog
$end
$timescale
	1ps
$end
$scope module testbench $end
$var wire 4 ! Y [3:0] $end
$var reg 4 " A [3:0] $end
$var reg 4 # B [3:0] $end
$var reg 3 $ S [2:0] $end
$scope module tb $end
$var wire 4 % A [3:0] $end
$var wire 4 & B [3:0] $end
$var wire 3 ' S [2:0] $end
$var reg 4 ( Y [3:0] $end
$upscope $end
$upscope $end
$enddefinitions $end
#0
$dumpvars
bx (
bx '
bx &
bx %
bx $
bx #
bx "
bx !
$end
#1
b10 !
b10 (
b0 $
b0 '
b11 #
b11 &
b10 "
b10 %
#2
b1111 !
b1111 (
b1 $
b1 '
b1011 #
b1011 &
b1100 "
b1100 %
#3
b10 $
b10 '
b101 #
b101 &
b1010 "
b1010 %
#4
b0 !
b0 (
b11 $
b11 '
b1111 #
b1111 &
b1111 "
b1111 %
#5
b1 !
b1 (
b100 $
b100 '
b0 #
b0 &
b1 "
b1 %
#6
b110 !
b110 (
b101 $
b101 '
b1001 #
b1001 &
b110 "
b110 %
#7
b1101 !
b1101 (
b110 $
b110 '
b1 #
b1 &
b1110 "
b1110 %
#8
b0 !
b0 (
b111 $
b111 '
b1011 #
b1011 &
b1101 "
b1101 %
