Lab09 D1/FFJK/FFJK.v
//Jonathan Pu c. 19249
//FF JK

module FFD(input wire clk, reset, En, D, output reg Q);

    always@(posedge clk or posedge reset) begin
        if(reset)
            Q <= 1'b0;
        else if (En)
            Q <= D;
    end
endmodule

module FFJK(input wire clk, reset, En, J, K, output wire Q);
    wire nK, nQ, a1, a2, D;
    not(nK, K);
    not(nQ, Q);
    and(a1, nK, Q);
    and(a2, J, nQ);
    or(D, a1, a2);    
    FFD a(clk, reset, En, D, Q);
endmodule

Lab09 D1/FFJK/FFJK_tb.v
//tb para FF JK

module testbench();
    reg clk;
    reg reset;
    reg En;
    reg J;
    reg K;
    wire Q;

    always
        #1 clk = ~clk;

    FFJK tb(clk, reset, En, J, K, Q);

    initial begin
        $display("\n");
        $display("FF tipo JK");
        $display("----------");
        $display("clk reset En J K | Q");
        $monitor("%b %b %b %b %b | %b", clk, reset, En, J, K, Q);
        clk = 0; reset = 1; En = 0; J = 0; K = 0;
        #2 reset = 0; En = 1; J = 0; K = 0;
        #2 J = 0; K = 0;
        #2 J = 1; K = 0;
        #2 J = 0; K = 1;
        #2 J = 1; K = 1;
        #2 J = 1; K = 1;
    end

    initial
        #14 $finish;

    //GTKWAVE
    initial begin
        $dumpfile("FFJK_tb.vcd"); //nombre del documento
        $dumpvars(0, testbench); //nombre del modulo
    end

endmodule

Lab09 D1/FFJK/FFJK_tb.vcd
$date
	Fri Oct 30 17:47:45 2020
$end
$version
	Icarus Verilog
$end
$timescale
	1ps
$end
$scope module testbench $end
$var wire 1 ! Q $end
$var reg 1 " En $end
$var reg 1 # J $end
$var reg 1 $ K $end
$var reg 1 % clk $end
$var reg 1 & reset $end
$scope module tb $end
$var wire 1 ' D $end
$var wire 1 " En $end
$var wire 1 # J $end
$var wire 1 $ K $end
$var wire 1 ( a1 $end
$var wire 1 ) a2 $end
$var wire 1 % clk $end
$var wire 1 * nK $end
$var wire 1 + nQ $end
$var wire 1 & reset $end
$var wire 1 ! Q $end
$scope module a $end
$var wire 1 ' D $end
$var wire 1 " En $end
$var wire 1 % clk $end
$var wire 1 & reset $end
$var reg 1 ! Q $end
$upscope $end
$upscope $end
$upscope $end
$enddefinitions $end
#0
$dumpvars
1+
1*
0)
0(
0'
1&
0%
0$
0#
0"
0!
$end
#1
1%
#2
0%
1"
0&
#3
1%
#4
0%
#5
1%
#6
1'
1)
0%
1#
#7
0)
1(
0+
1!
1%
#8
0'
0(
0*
0%
1$
0#
#9
1+
0!
1%
#10
1'
1)
0%
1#
#11
0'
0)
0+
1!
1%
#12
0%
#13
1'
1)
1+
0!
1%
