Lab09 D1/Lookup/Lookup.v
//Jonathan Pu c. 19249
//ROM como lookup table

module opcode(input wire [6:0]address1,
              
              output reg [12:0]data1);

    always @(address1)
        begin
            casex(address1)
                7'bxxxxxx0: data1 <= 13'b1000000001000;
                7'b00001x1: data1 <= 13'b0100000001000;
                7'b00000x1: data1 <= 13'b1000000001000;
                7'b00011x1: data1 <= 13'b1000000001000;
                7'b00010x1: data1 <= 13'b0100000001000;
                7'b0010xx1: data1 <= 13'b0001001000010;
                7'b0011xx1: data1 <= 13'b1001001100000;
                7'b0100xx1: data1 <= 13'b0011010000010;
                7'b0101xx1: data1 <= 13'b0011010000100;
                7'b0110xx1: data1 <= 13'b1011010100000;
                7'b0111xx1: data1 <= 13'b1000000111000;
                7'b1000x11: data1 <= 13'b0100000001000;
                7'b1000x01: data1 <= 13'b1000000001000;
                7'b1001x11: data1 <= 13'b1000000001000;
                7'b1001x01: data1 <= 13'b0100000001000;
                7'b1010xx1: data1 <= 13'b0011011000010;
                7'b1011xx1: data1 <= 13'b1011011100000;
                7'b1100xx1: data1 <= 13'b0100000001000;
                7'b1101xx1: data1 <= 13'b0000000001001;
                7'b1110xx1: data1 <= 13'b0011100000010;
                7'b1111xx1: data1 <= 13'b1011100100000;
            endcase
        end
               
endmodule

Lab09 D1/Lookup/Lookup_tb.v
//tb para lookup table

module testbench();
    reg [6:0]address1;
    
    wire [12:0]data1;

    opcode a(address1, data1);

    initial begin
        $display("\n");
        $display("Testbench instrucciones");
        $display("--------------------");
        $display("    Address1         |      Data1    ");
        $monitor("    %b    |    %b    ",address1, data1);
        address1 = 7'bxxxxxx0;
        #1 address1 = 7'b00001x1;
        #1 address1 = 7'b00000x1;
        #1 address1 = 7'b00011x1;
        #1 address1 = 7'b00010x1;
        #1 address1 = 7'b0010xx1;
        #1 address1 = 7'b0011xx1;
        #1 address1 = 7'b0100xx1;
        #1 address1 = 7'b0101xx1;
        #1 address1 = 7'b0110xx1;
        #1 address1 = 7'b0111xx1;
        #1 address1 = 7'b1000x11;
        #1 address1 = 7'b1000x01;
        #1 address1 = 7'b1001x11;
        #1 address1 = 7'b1001x01;
        #1 address1 = 7'b1010xx1;
        #1 address1 = 7'b1011xx1;
        #1 address1 = 7'b1100xx1;
        #1 address1 = 7'b1101xx1;
        #1 address1 = 7'b1110xx1;
        #1 address1 = 7'b1111xx1;
        //prueba para los dont care
        #1 address1 = 7'b0000000;
        #1 address1 = 7'b0101010;
        #1 address1 = 7'b1111110;
        #1 address1 = 7'b1000000;
        #1 address1 = 7'b0110010;
    end

    initial
        #35 $finish;

    //GTK WAVE
    initial begin
        $dumpfile("Lookup_tb.vcd"); //nombre del documento
        $dumpvars(0, testbench);
    end

endmodule

Lab09 D1/Lookup/Lookup_tb.vcd
$date
	Fri Oct 30 21:33:01 2020
$end
$version
	Icarus Verilog
$end
$timescale
	1ps
$end
$scope module testbench $end
$var wire 13 ! data1 [12:0] $end
$var reg 7 " address1 [6:0] $end
$scope module a $end
$var wire 7 # address1 [6:0] $end
$var reg 13 $ data1 [12:0] $end
$upscope $end
$upscope $end
$enddefinitions $end
#0
$dumpvars
b1000000001000 $
bx0 #
bx0 "
b1000000001000 !
$end
#1
b100000001000 !
b100000001000 $
b1x1 "
b1x1 #
#2
b1000000001000 !
b1000000001000 $
b0x1 "
b0x1 #
#3
b11x1 "
b11x1 #
#4
b100000001000 !
b100000001000 $
b10x1 "
b10x1 #
#5
b1001000010 !
b1001000010 $
b10xx1 "
b10xx1 #
#6
b1001001100000 !
b1001001100000 $
b11xx1 "
b11xx1 #
#7
b11010000010 !
b11010000010 $
b100xx1 "
b100xx1 #
#8
b11010000100 !
b11010000100 $
b101xx1 "
b101xx1 #
#9
b1011010100000 !
b1011010100000 $
b110xx1 "
b110xx1 #
#10
b1000000111000 !
b1000000111000 $
b111xx1 "
b111xx1 #
#11
b100000001000 !
b100000001000 $
b1000x11 "
b1000x11 #
#12
b1000000001000 !
b1000000001000 $
b1000x01 "
b1000x01 #
#13
b1001x11 "
b1001x11 #
#14
b100000001000 !
b100000001000 $
b1001x01 "
b1001x01 #
#15
b11011000010 !
b11011000010 $
b1010xx1 "
b1010xx1 #
#16
b1011011100000 !
b1011011100000 $
b1011xx1 "
b1011xx1 #
#17
b100000001000 !
b100000001000 $
b1100xx1 "
b1100xx1 #
#18
b1001 !
b1001 $
b1101xx1 "
b1101xx1 #
#19
b11100000010 !
b11100000010 $
b1110xx1 "
b1110xx1 #
#20
b1011100100000 !
b1011100100000 $
b1111xx1 "
b1111xx1 #
#21
b1000000001000 !
b1000000001000 $
b0 "
b0 #
#22
b101010 "
b101010 #
#23
b1111110 "
b1111110 #
#24
b1000000 "
b1000000 #
#25
b110010 "
b110010 #
