Lab04 D1/Ejercicio05(Alarma)/Lab05Ejercicio05.v
// Ejercicio05 Lab05 Jonathan Pu c. 19249

// Gate modelling
//SOP L = A*M'*P' + A*M*P' + A*M*P

module SOP(input wire inA, inM, inP, output wire L);

    wire NM, NP, A1, A2, A3;
    not (NM, inM);
    not (NP, inP);
    and (A1, inA, NM, NP);
    and (A2, inA, inM, NP);
    and (A3, inA, inM, inP);
    or (L, A1, A2, A3);

endmodule

//POS L = (A + M + P)*(A + M + P')*(A + M' + P)*(A + M' + P')*(A' + M + P')

module POS(input wire inA, inM, inP, output wire L);

    wire NA, NM, NP, o1, o2, o3, o4, o5;
    not (NA, inA);
    not (NM, inM);
    not (NP, inP);
    or (o1, inA, inM, inP);
    or (o2, inA, inM, NP);
    or (o3, inA, NM, inP);
    or (o4, inA, NM, NP);
    or (o5, NA, inM, NP);
    and (L, o1, o2, o3, o4, o5);

endmodule

//Simplificada L = A*M + A*P'

module SIMP(input wire inA, inM, inP, output wire L);

    wire NP, A1, A2;
    not (NP, inP);
    and (A1, inA, inM);
    and (A2, inA, NP);
    or (L, A1, A2);

endmodule

//Behavioral modelling
//SOP L = A*M'*P' + A*M*P' + A*M*P
    module SOP1(input wire inA, inM, inP, output wire L);

        assign L = (inA & ~inM & ~inP) | (inA & inM & ~inP) 
        | (inA & inM & inP);
    
    endmodule
    
//POS L = (A + M + P)*(A + M + P')*(A + M' + P)*(A + M' + P')*(A' + M + P')
    module POS1(input wire inA, inM, inP, output wire L);

        assign L = (inA | inM | inP) & (inA | inM | ~inP) 
        & (inA | ~inM | inP) & (inA | ~inM | ~inP) & (~inA | inM | ~inP);

    endmodule

//Simplificada L = A*M + A*P'
    module SIMP1(input wire inA, inM, inP, output wire L);
        assign L = (inA & inM) | (inA & ~inP);

    endmodule

Lab04 D1/Ejercicio05(Alarma)/Lab05Ejercicio05_tb.v
// Jonathan Pu c. 19249

module testbench05();
    //gate modelling

    reg p1, p2, p3;
    wire out1, out2, out3;

    //SOP 
    SOP S1(p1, p2, p3, out1);
     
    initial begin
        #1
        $display("\n");
        $display("Tabla SOP1 GM");
        $display("A  M  P  |  L");
        $display("---------|---");
        $monitor("%b  %b  %b  |  %b", p1, p2, p3, out1);
           //Entradas comienzan en 0
           p1 = 0; p2 = 0; p3 =0;
       #1 p3 = 1;
       #1 p2 = 1; p3 = 0;
       #1 p3 = 1;
       #1 p1 = 1; p2 = 0; p3 = 0;
       #1 p3 = 1;
       #1 p2 = 1; p3 =0; 
       #1 p3 = 1;

    end

    //POS
    POS P1(p1, p2, p3, out2);

    initial begin
        #9
        $display("\n");
        $display("Tabla POS1 GM");
        $display("A  M  P  |  L");
        $display("---------|---");
        $monitor("%b  %b  %b  |  %b", p1, p2, p3, out2);
             //Entradas comienzan en 0
           p1 = 0; p2 = 0; p3 =0;
       #1 p3 = 1;
       #1 p2 = 1; p3 = 0;
       #1 p3 = 1;
       #1 p1 = 1; p2 = 0; p3 = 0;
       #1 p3 = 1;
       #1 p2 = 1; p3 =0; 
       #1 p3 = 1;

    end

    //Simplificada
    SIMP SO1(p1, p2, p3, out3);
    
    initial begin
         #17
        $display("\n");
        $display("Tabla SIMP 1 ");
        $display("A  M  P  |  L");
        $display("---------|---");
        $monitor("%b  %b  %b  |  %b", p1, p2, p3, out3);
             //Entradas comienzan en 0
           p1 = 0; p2 = 0; p3 =0;
       #1 p3 = 1;
       #1 p2 = 1; p3 = 0;
       #1 p3 = 1;
       #1 p1 = 1; p2 = 0; p3 = 0;
       #1 p3 = 1;
       #1 p2 = 1; p3 =0; 
       #1 p3 = 1;

    end

    //behavioral modelling
    reg p4, p5, p6;
    wire out4, out5, out6;

    //SOP1

    SOP1 S2(p4, p5, p6, out4);

    initial begin
        #25
        $display("\n");
        $display("Tabla SOP2 BM");
        $display("A  M  P  |  L");
        $display("---------|---");
        $monitor("%b  %b  %b  |  %b", p4, p5, p6, out4);
             //Entradas comienzan en 0
           p4 = 0; p5 = 0; p6 =0;
       #1 p6 = 1;
       #1 p5 = 1; p6 = 0;
       #1 p6 = 1;
       #1 p4 = 1; p5 = 0; p6 = 0;
       #1 p6 = 1;
       #1 p5 = 1; p6 =0; 
       #1 p6 = 1;

    end

    //POS1

    POS1 P2(p4, p5, p6, out5);
    initial begin
        #33
        $display("\n");
        $display("Tabla POS2 BM");
        $display("A  M  P  |  L");
        $display("---------|---");
        $monitor("%b  %b  %b  |  %b", p4, p5, p6, out5);
             //Entradas comienzan en 0
           p4 = 0; p5 = 0; p6 =0;
       #1 p6 = 1;
       #1 p5 = 1; p6 = 0;
       #1 p6 = 1;
       #1 p4 = 1; p5 = 0; p6 = 0;
       #1 p6 = 1;
       #1 p5 = 1; p6 =0; 
       #1 p6 = 1;

    end

    //SIMP1

    SIMP1 SO2(p4, p5, p6, out6);
    initial begin
        #41
        $display("\n");
        $display("Tabla SIMP 2 ");
        $display("A  M  P  |  L");
        $display("---------|---");
        $monitor("%b  %b  %b  |  %b", p4, p5, p6, out6);
             //Entradas comienzan en 0
           p4 = 0; p5 = 0; p6 =0;
       #1 p6 = 1;
       #1 p5 = 1; p6 = 0;
       #1 p6 = 1;
       #1 p4 = 1; p5 = 0; p6 = 0;
       #1 p6 = 1;
       #1 p5 = 1; p6 =0; 
       #1 p6 = 1;

    end
//Fin de codigo
    initial
    #49 $finish;

//GTK Wave
    initial begin
        $dumpfile("Lab05Ejercicio05_tb.vcd");
        $dumpvars(0, testbench05);

    end

endmodule
//Fin de modulo de testbench para todas las formas del ejercicio05

Lab04 D1/Ejercicio05(Alarma)/Lab05Ejercicio05_tb.vcd
$date
	Sun Aug 09 06:04:58 2020
$end
$version
	Icarus Verilog
$end
$timescale
	1ps
$end
$scope module testbench05 $end
$var wire 1 ! out6 $end
$var wire 1 " out5 $end
$var wire 1 # out4 $end
$var wire 1 $ out3 $end
$var wire 1 % out2 $end
$var wire 1 & out1 $end
$var reg 1 ' p1 $end
$var reg 1 ( p2 $end
$var reg 1 ) p3 $end
$var reg 1 * p4 $end
$var reg 1 + p5 $end
$var reg 1 , p6 $end
$scope module P1 $end
$var wire 1 % L $end
$var wire 1 - NA $end
$var wire 1 . NM $end
$var wire 1 / NP $end
$var wire 1 ' inA $end
$var wire 1 ( inM $end
$var wire 1 ) inP $end
$var wire 1 0 o1 $end
$var wire 1 1 o2 $end
$var wire 1 2 o3 $end
$var wire 1 3 o4 $end
$var wire 1 4 o5 $end
$upscope $end
$scope module P2 $end
$var wire 1 " L $end
$var wire 1 * inA $end
$var wire 1 + inM $end
$var wire 1 , inP $end
$upscope $end
$scope module S1 $end
$var wire 1 5 A1 $end
$var wire 1 6 A2 $end
$var wire 1 7 A3 $end
$var wire 1 & L $end
$var wire 1 8 NM $end
$var wire 1 9 NP $end
$var wire 1 ' inA $end
$var wire 1 ( inM $end
$var wire 1 ) inP $end
$upscope $end
$scope module S2 $end
$var wire 1 # L $end
$var wire 1 * inA $end
$var wire 1 + inM $end
$var wire 1 , inP $end
$upscope $end
$scope module SO1 $end
$var wire 1 : A1 $end
$var wire 1 ; A2 $end
$var wire 1 $ L $end
$var wire 1 < NP $end
$var wire 1 ' inA $end
$var wire 1 ( inM $end
$var wire 1 ) inP $end
$upscope $end
$scope module SO2 $end
$var wire 1 ! L $end
$var wire 1 * inA $end
$var wire 1 + inM $end
$var wire 1 , inP $end
$upscope $end
$upscope $end
$enddefinitions $end
#0
$dumpvars
x<
x;
x:
x9
x8
x7
x6
x5
x4
x3
x2
x1
x0
x/
x.
x-
x,
x+
x*
x)
x(
x'
x&
x%
x$
x#
x"
x!
$end
#1
0%
11
12
13
0&
0$
1/
19
1<
1.
14
18
1-
00
05
06
07
0:
0;
0)
0(
0'
#2
0%
01
0/
10
09
0<
1)
#3
1/
02
19
1<
0.
11
08
0)
1(
#4
0%
03
0/
12
09
0<
1)
#5
1%
1$
1&
1;
15
1/
19
1<
1.
14
18
0-
13
0)
0(
1'
#6
0%
0&
0$
04
05
0;
0/
09
0<
1)
#7
1&
1%
16
1;
1$
1/
19
1<
0.
14
08
1:
0)
1(
#8
06
0;
0/
09
17
0<
1)
#9
0%
0&
0$
1/
19
1<
1.
18
1-
00
11
12
13
07
0:
0)
0(
0'
#10
0%
01
0/
10
09
0<
1)
#11
1/
02
19
1<
0.
11
08
0)
1(
#12
0%
03
0/
12
09
0<
1)
#13
1%
1$
1&
1;
15
1/
19
1<
1.
14
18
0-
13
0)
0(
1'
#14
0%
0&
0$
04
05
0;
0/
09
0<
1)
#15
1&
1%
16
1;
1$
1/
19
1<
0.
14
08
1:
0)
1(
#16
06
0;
0/
09
17
0<
1)
#17
0%
0&
0$
1/
19
1<
1.
18
1-
00
11
12
13
07
0:
0)
0(
0'
#18
0%
01
0/
10
09
0<
1)
#19
1/
02
19
1<
0.
11
08
0)
1(
#20
0%
03
0/
12
09
0<
1)
#21
1%
1$
1&
1;
15
1/
19
1<
1.
14
18
0-
13
0)
0(
1'
#22
0%
0&
0$
04
05
0;
0/
09
0<
1)
#23
1&
1%
16
1;
1$
1/
19
1<
0.
14
08
1:
0)
1(
#24
06
0;
0/
09
17
0<
1)
#25
0"
0#
0!
0,
0+
0*
#26
1,
#27
0,
1+
#28
1,
#29
1#
1"
1!
0,
0+
1*
#30
0#
0"
0!
1,
#31
1#
1"
1!
0,
1+
#32
1,
#33
0"
0#
0!
0,
0+
0*
#34
1,
#35
0,
1+
#36
1,
#37
1#
1"
1!
0,
0+
1*
#38
0#
0"
0!
1,
#39
1#
1"
1!
0,
1+
#40
1,
#41
0"
0#
0!
0,
0+
0*
#42
1,
#43
0,
1+
#44
1,
#45
1#
1"
1!
0,
0+
1*
#46
0#
0"
0!
1,
#47
1#
1"
1!
0,
1+
#48
1,
