Lab08 D1/Contador12bits/Contador12bits.v
//JOnathan Pu c. 19249
//Contador de 12 bits con enable y load

module cont12(
    input wire clk,
    input wire reset,
    input wire enable,
    input wire loact, //bit que activa la carga
    input wire [11:0]load, //carga de 12bits
    output reg [11:0]cont //salida de 12bits
    );

        always @(posedge clk or posedge reset or loact or load) begin //si LA y load cambia tambien se ejecuta el always
            if (reset)
                cont <= 12'b000000000000; //comienza en cero el contador
            else if (loact)
                cont <= load; //si el enable esta desactivado, el load pasa a la salida
            else if (enable)
                cont <= cont + 1; //a lo que tenia la salida se le suma 1
        end

endmodule

Lab08 D1/Contador12bits/Contador12bits_tb.v
//Testbench para contador de 12 bits

module testbench();
    reg clk;
    reg reset;
    reg enable;
    reg loact;
    reg [11:0]load;
    wire [11:0]cont;

    always
        #1 clk = ~clk;
  
    cont12 contador1(clk, reset, enable, loact, load, cont);
    
        initial begin
        //llamar el modulo cont12
       
        $display("\n");
        $display("Testbench contador 12 bits");
        $display("--------------------------");
        $display(" clk  reset  enable  loact    load      |   count ");
        $monitor(" %b     %b      %b      %b     %b |   %b ", clk, reset, enable, loact, load, cont);
        clk = 0; reset = 1; enable = 0; loact = 0; load = 0; //se resetea el contador
        #1 reset = 0; enable = 1;
        #1 reset = 0; enable = 1; //varios tiempos para verificar que cuente varios bits
        #10 enable = 0; loact = 1; load = 12'b000111000111; //prueba del load
        #1 reset = 0; load = 12'b000111000111;
        #5 reset = 0; enable = 1; loact = 0; //prueba de seguir contando
        #5 reset = 0; enable = 1;
        #1 reset = 1; //volver a resetear la salida

    end

    initial
        #50 $finish;

    //GTK WAVE
    initial begin
        $dumpfile("Contador12bits_tb.vcd"); //nombre del documento
        $dumpvars(0, testbench); //modulo de testbench
    end

endmodule

Lab08 D1/Contador12bits/Contador12bits_tb.vcd
$date
	Thu Oct 29 20:31:54 2020
$end
$version
	Icarus Verilog
$end
$timescale
	1ps
$end
$scope module testbench $end
$var wire 12 ! cont [11:0] $end
$var reg 1 " clk $end
$var reg 1 # enable $end
$var reg 1 $ loact $end
$var reg 12 % load [11:0] $end
$var reg 1 & reset $end
$scope module contador1 $end
$var wire 1 " clk $end
$var wire 1 # enable $end
$var wire 1 $ loact $end
$var wire 12 ' load [11:0] $end
$var wire 1 & reset $end
$var reg 12 ( cont [11:0] $end
$upscope $end
$upscope $end
$enddefinitions $end
#0
$dumpvars
b0 (
b0 '
1&
b0 %
0$
0#
0"
b0 !
$end
#1
b1 !
b1 (
1#
0&
1"
#2
0"
#3
b10 !
b10 (
1"
#4
0"
#5
b11 !
b11 (
1"
#6
0"
#7
b100 !
b100 (
1"
#8
0"
#9
b101 !
b101 (
1"
#10
0"
#11
b110 !
b110 (
1"
#12
b111000111 !
b111000111 (
0"
b111000111 %
b111000111 '
1$
0#
#13
1"
#14
0"
#15
1"
#16
0"
#17
1"
#18
b111001000 !
b111001000 (
0"
0$
1#
#19
b111001001 !
b111001001 (
1"
#20
0"
#21
b111001010 !
b111001010 (
1"
#22
0"
#23
b111001011 !
b111001011 (
1"
#24
b0 !
b0 (
0"
1&
