Lab09 D1/FFTipoD/FFD.v
//Jonathan Pu c. 19249
//FF tipo D
//un bit
module FFD(input wire clk, reset, En, D, output reg Q);

    always@(posedge clk or posedge reset) begin
        if(reset)
            Q <= 1'b0;
        else if (En)
            Q <= D;
    end
endmodule

//dos bits
module FFD2(input wire clk, reset, En,
            input wire [1:0]D2,
            output wire [1:0]Q2);

    FFD a(clk, reset, En, D2[1], Q2[1]);
    FFD b(clk, reset, En, D2[0], Q2[0]);
endmodule

//cuatro bits
module FFD4(input wire clk, reset, En,
            input wire [3:0]D4,
            output wire [3:0]Q4);
    
    FFD2 a(clk, reset, En, D4[3:2], Q4[3:2]);
    FFD2 b(clk, reset, En, D4[1:0], Q4[1:0]);
endmodule

Lab09 D1/FFTipoD/FFD_tb.v
//tb para FFDs
//FFD un bit
module testbencha();

    reg clk;
    reg reset;
    reg en;
    reg D;
    reg [1:0]D2;
    reg [3:0]D4;
    wire Q;
    wire [1:0]Q2;
    wire [3:0]Q4;

    always
        #1 clk = ~clk;
    
    FFD a(clk, reset, en, D, Q);
    FFD2 b(clk, reset, en, D2[1:0], Q2[1:0]);
    FFD4 c(clk, reset, en, D4[3:0], Q4[3:0]);


        initial begin
            $display("\n");
            $display("Testbench FF tipo D");
            $display("-----------------------------");
            $display("clk  reset  en  D  D2[1]  D2[0]  D4[3]  D4[2]  D4[1]  D4[0]|  Q  Q2[1]  Q2[0]  Q4[3]  Q4[2]  Q4[1]  Q4[0]");
            $display("-----------------------------");
            $monitor(" %b  %b  %b  %b  %b  %b  %b  %b  %b  %b  |  %b  %b  %b  %b  %b  %b  %b", clk, reset, en, D, D2[1], D2[0], D4[3], D4[2], D4[1], D4[0], Q, Q2[1], Q2[0], Q4[3], Q4[2], Q4[1], Q4[0]);
            clk = 0; reset = 1; en = 0; D = 0; D2[1] = 0; D2[0] = 0; D4[3] = 0; D4[2] = 0; D4[1] = 0; D4[0] = 0; 
            #1 reset = 1; en = 1; D = 0; D2[1] = 0; D2[0] = 0; D4[3] = 0; D4[2] = 0; D4[1] = 0; D4[0] = 0; 
            #5 reset = 0; en = 1; D = 1; D2[1] = 1; D2[0] = 1; D4[3] = 1; D4[2] = 0; D4[1] = 1; D4[0] = 1; 
            #2 en = 0; D = 0; D2[1] = 0; D2[0] = 1; D4[3] = 0; D4[2] = 0; D4[1] = 1; D4[0] = 1; 
            #5 en = 1; D = 1; D2[1] = 1; D2[0] = 1; D4[3] = 1; D4[2] = 0; D4[1] = 1; D4[0] = 1; 
            #10 reset = 1; 
        end

    initial
        #30 $finish;
    
    //GTK WAVE
    initial begin
        $dumpfile("FFD_tb.vcd"); //nombre del documento
        $dumpvars(0, testbencha); //nombre del modulo
    end
 
endmodule

Lab09 D1/FFTipoD/FFD_tb.vcd
$date
	Thu Oct 29 23:21:56 2020
$end
$version
	Icarus Verilog
$end
$timescale
	1ps
$end
$scope module testbencha $end
$var wire 4 ! Q4 [3:0] $end
$var wire 2 " Q2 [1:0] $end
$var wire 1 # Q $end
$var reg 1 $ D $end
$var reg 2 % D2 [1:0] $end
$var reg 4 & D4 [3:0] $end
$var reg 1 ' clk $end
$var reg 1 ( en $end
$var reg 1 ) reset $end
$scope module a $end
$var wire 1 $ D $end
$var wire 1 ( En $end
$var wire 1 ' clk $end
$var wire 1 ) reset $end
$var reg 1 # Q $end
$upscope $end
$scope module b $end
$var wire 2 * D2 [1:0] $end
$var wire 1 ( En $end
$var wire 1 ' clk $end
$var wire 1 ) reset $end
$var wire 2 + Q2 [1:0] $end
$scope module a $end
$var wire 1 , D $end
$var wire 1 ( En $end
$var wire 1 ' clk $end
$var wire 1 ) reset $end
$var reg 1 - Q $end
$upscope $end
$scope module b $end
$var wire 1 . D $end
$var wire 1 ( En $end
$var wire 1 ' clk $end
$var wire 1 ) reset $end
$var reg 1 / Q $end
$upscope $end
$upscope $end
$scope module c $end
$var wire 4 0 D4 [3:0] $end
$var wire 1 ( En $end
$var wire 1 ' clk $end
$var wire 1 ) reset $end
$var wire 4 1 Q4 [3:0] $end
$scope module a $end
$var wire 2 2 D2 [1:0] $end
$var wire 1 ( En $end
$var wire 1 ' clk $end
$var wire 1 ) reset $end
$var wire 2 3 Q2 [1:0] $end
$scope module a $end
$var wire 1 4 D $end
$var wire 1 ( En $end
$var wire 1 ' clk $end
$var wire 1 ) reset $end
$var reg 1 5 Q $end
$upscope $end
$scope module b $end
$var wire 1 6 D $end
$var wire 1 ( En $end
$var wire 1 ' clk $end
$var wire 1 ) reset $end
$var reg 1 7 Q $end
$upscope $end
$upscope $end
$scope module b $end
$var wire 2 8 D2 [1:0] $end
$var wire 1 ( En $end
$var wire 1 ' clk $end
$var wire 1 ) reset $end
$var wire 2 9 Q2 [1:0] $end
$scope module a $end
$var wire 1 : D $end
$var wire 1 ( En $end
$var wire 1 ' clk $end
$var wire 1 ) reset $end
$var reg 1 ; Q $end
$upscope $end
$scope module b $end
$var wire 1 < D $end
$var wire 1 ( En $end
$var wire 1 ' clk $end
$var wire 1 ) reset $end
$var reg 1 = Q $end
$upscope $end
$upscope $end
$upscope $end
$upscope $end
$enddefinitions $end
#0
$dumpvars
0=
0<
0;
0:
b0 9
b0 8
07
06
05
04
b0 3
b0 2
b0 1
b0 0
0/
0.
0-
0,
b0 +
b0 *
1)
0(
0'
b0 &
b0 %
0$
0#
b0 "
b0 !
$end
#1
1(
1'
#2
0'
#3
1'
#4
0'
#5
1'
#6
1:
1<
14
b11 8
b10 2
1.
1,
0'
b1011 &
b1011 0
b11 %
b11 *
1$
0)
#7
1#
1-
b11 "
b11 +
1/
b10 3
15
1;
b1011 !
b1011 1
b11 9
1=
1'
#8
04
b0 2
0,
0'
b11 &
b11 0
b1 %
b1 *
0$
0(
#9
1'
#10
0'
#11
1'
#12
0'
#13
b11 !
b11 1
b0 3
05
14
b10 2
1,
1'
b1011 &
b1011 0
b11 %
b11 *
1$
1(
#14
0'
#15
b1011 !
b1011 1
b10 3
15
1'
#16
0'
#17
1'
#18
0'
#19
1'
#20
0'
#21
1'
#22
0'
#23
0#
0-
b0 "
b0 +
0/
b0 3
05
0;
b0 !
b0 1
b0 9
0=
1'
1)
